Workbook
Name Slicer_Model_Name1: #N/A
Name Slicer_Model_Name2: #N/A

Sheet Data_Sheet
A1: SL No. | B1: Product_ID | C1: City_Category | D1: Batch | E1: Model Name | F1: Delivery Status | G1: Product Cost | H1: Taxation & Delivery Cost | I1: Final Cost | J1: On Road Price
A2: 1 | B2: TATA001 | C2: Metro | D2: B001 | E2: Tata Nexon | F2: Delivered | G2: 780000 | H2: 120000 | I2: 900000 | J2: 1200000
A3: 2 | B3: TATA002 | C3: Tier 1 | D3: B001 | E3: Tata Punch | F3: Delivered | G3: 620000 | H3: 95000 | I3: 715000 | J3: 950000
A4: 3 | B4: TATA003 | C4: Tier 2 | D4: B002 | E4: Tata Tiago | F4: Delivered | G4: 520000 | H4: 80000 | I4: 600000 | J4: 750000
A5: 4 | B5: TATA004 | C5: Metro | D5: B002 | E5: Tata Harrier | F5: Delivered | G5: 1450000 | H5: 250000 | I5: 1700000 | J5: 2100000
A6: 5 | B6: TATA005 | C6: Tier 1 | D6: B003 | E6: Tata Safari | F6: Pending | G6: 1550000 | H6: 270000 | I6: 1820000 | J6: 2300000
A7: 6 | B7: TATA006 | C7: Metro | D7: B003 | E7: Tata Altroz | F7: Delivered | G7: 680000 | H7: 105000 | I7: 785000 | J7: 1000000
A8: 7 | B8: TATA007 | C8: Tier 2 | D8: B004 | E8: Tata Tigor | F8: Delivered | G8: 610000 | H8: 90000 | I8: 700000 | J8: 850000
A9: 8 | B9: TATA008 | C9: Tier 1 | D9: B004 | E9: Tata Curvv | F9: Pending | G9: 1050000 | H9: 175000 | I9: 1225000 | J9: 1700000
A10: 9 | B10: TATA009 | C10: Metro | D10: B005 | E10: Tata Nexon EV | F10: Delivered | G10: 1450000 | H10: 180000 | I10: 1630000 | J10: 1500000
A11: 10 | B11: TATA010 | C11: Tier 2 | D11: B005 | E11: Tata Punch EV | F11: In Transit | G11: 1150000 | H11: 155000 | I11: 1305000 | J11: 1150000
A12: 11 | B12: TATA011 | C12: Metro | D12: B006 | E12: Tata Tiago EV | F12: Delivered | G12: 950000 | H12: 130000 | I12: 1080000 | J12: 900000
A13: 12 | B13: TATA012 | C13: Tier 1 | D13: B006 | E13: Tata Altroz | F13: Delivered | G13: 720000 | H13: 110000 | I13: 830000 | J13: 1000000
... A51: 50 | B51: TATA050 | C51: Metro | D51: B025 | E51: Tata Nexon | F51: Delivered | G51: 880000 | H51: 135000 | I51: 1015000 | J51: 1200000
A54: Column1 | B54: Production cost | C54: delivery and tax | D54: total price | E54: estimated profit | F54: total cost
A55: Total | B55: =SUM(G2:G51) -> 51250000 | C55: =SUM(H2:H51) -> 7922000 | D55: =SUM(J2:J51) -> 67100000 | E55: =D55-F55 -> 7928000 | F55: =SUM(B55:C55) -> 59172000
A56: Total generated revenue | B56: Unrealised P&L | C56: Realised P&L | D56: Estimated P&L
A57: =SUMIF(Table1[Delivery Status],F4,Table1[On Road Price]) -> 45600000 | B57: =A57-SUM(Table1[Product Cost]) -> -5650000 | C57: =B57+SUM(H2:H51) -> 2272000 | D57: =D55-F55 -> 7928000
H60: =Table9[total cost] -> 59172000
E63: =Table10[Estimated P&L] -> 7928000
D64: =Table10[Realised P&L] -> 2272000
C65: =Table10[Unrealised P&L] -> -5650000
B66: =Table10[Total generated revenue] -> 45600000

Sheet Dashboard
A5: Select Car Model: | C5: Tata Tigor | D5: Units Sold | F5: Total Revenue | H5: Avg Sale Price | J5: Total Product Cost | L5: Tax & Delivery Cost
D6: =COUNTIFS(Table1[Model Name],$C$5) -> 5 | F6: =SUMIFS(Table1[On Road Price],Table1[Model Name],$C$5) -> 4250000 | H6: =IFERROR(AVERAGEIFS(Table1[On Road Price],Table1[Model Name],$C$5),0) -> 850000 | J6: =SUMIFS(Table1[Product Cost],Table1[Model Name],$C$5) -> 3170000 | L6: =SUMIFS(Table1[Taxation & Delivery Cost],Table1[Model Name],$C$5) -> 475000
A9: Total generated revenue : | C9: =Data_Sheet!B66 -> 45600000 | D9: Unrealised P&L : | G9: =Data_Sheet!C65 -> -5650000 | I9: Realised P&L : | K9: =Data_Sheet!D64 -> 2272000 | L9: Estimated P&L : | N9: =Data_Sheet!E63 -> 7928000 | P9: Total Cost : | Q9: =Data_Sheet!H60 -> 59172000
A11: City Category | C11: Units Sold | D11: Total Revenue | G11: Avarage Sale Price | K11: Delivery Status | L11: Count
A12: Metro | C12: =COUNTIFS(Table1[Model Name],$C$5,Table1[City_Category],$A12) -> 1 | D12: =SUMIFS(Table1[Final Cost],Table1[Model Name],$C$5,Table1[City_Category],$A12) -> 743000 | G12: =IFERROR(AVERAGEIFS(Table1[Final Cost],Table1[Model Name],$C$5,Table1[City_Category],$A12),0) -> 743000 | K12: Delivered | L12: =COUNTIFS(Table1[Model Name],$C$5,Table1[Delivery Status],$K12) -> 4
A13: Tier 1 | C13: =COUNTIFS(Table1[Model Name],$C$5,Table1[City_Category],$A13) -> 2 | D13: =SUMIFS(Table1[Final Cost],Table1[Model Name],$C$5,Table1[City_Category],$A13) -> 1485000 | G13: =IFERROR(AVERAGEIFS(Table1[Final Cost],Table1[Model Name],$C$5,Table1[City_Category],$A13),0) -> 742500 | K13: Pending | L13: =COUNTIFS(Table1[Model Name],$C$5,Table1[Delivery Status],$K13) -> 1
A14: Tier 2 | C14: =COUNTIFS(Table1[Model Name],$C$5,Table1[City_Category],$A14) -> 2 | D14: =SUMIFS(Table1[Final Cost],Table1[Model Name],$C$5,Table1[City_Category],$A14) -> 1417000 | G14: =IFERROR(AVERAGEIFS(Table1[Final Cost],Table1[Model Name],$C$5,Table1[City_Category],$A14),0) -> 708500 | K14: In Transit | L14: =COUNTIFS(Table1[Model Name],$C$5,Table1[Delivery Status],$K14) -> 0
A15: Grand Total | C15: =COUNTIFS(Table1[Model Name],$C$5) -> 5 | D15: =SUMIFS(Table1[Final Cost],Table1[Model Name],$C$5) -> 3645000 | G15: =IFERROR(D15/C15,0) -> 729000 | K15: Total | L15: =COUNTIFS(Table1[Model Name],$C$5) -> 5
B16: Row Labels | C16: Sum of Cars Sold
B17: Metro | C17: 17
B18: Tier 1 | C18: 11
B19: Tier 2 | C19: 7
B20: Grand Total | C20: 35

Sheet Sale_analysis
A1: Product Status | B1: Total Count
A2: In Transit | B2: =COUNTIF(Table1[Delivery Status],Sale_analysis!A2) -> 7

Sheet City_category
A3: Sum of Product Cost | B3: Column Labels
A4: Row Labels | B4: Metro | C4: Tier 1 | D4: Tier 2 | E4: Grand Total
A5: Tata Altroz | B5: 2130000 | C5: 1455000 | E5: 3585000
A6: Tata Curvv | B6: 2180000 | C6: 2170000 | D6: 1150000 | E6: 5500000
A7: Tata Harrier | B7: 4450000 | C7: 1550000 | D7: 1500000 | E7: 7500000
A8: Tata Nexon | B8: 2510000 | C8: 870000 | D8: 1620000 | E8: 5000000
A9: Tata Nexon EV | B9: 2930000 | C9: 1500000 | D9: 1520000 | E9: 5950000
A10: Tata Punch | B10: 670000 | C10: 1300000 | D10: 1285000 | E10: 3255000
A11: Tata Punch EV | B11: 1220000 | C11: 1180000 | D11: 2350000 | E11: 4750000
A12: Tata Safari | B12: 1650000 | C12: 4750000 | D12: 1600000 | E12: 8000000
A13: Tata Tiago | D13: 1610000 | E13: 1610000
A14: Tata Tiago EV | B14: 1950000 | C14: 980000 | E14: 2930000
A15: Tata Tigor | B15: 645000 | C15: 1290000 | D15: 1235000 | E15: 3170000
A16: Grand Total | B16: 20335000 | C16: 17045000 | D16: 13870000 | E16: 51250000

Sheet Model wise Analysis
A1: Model | B1: Delivered | C1: Pending | D1: In Transit
A2: Tata Nexon | B2: =COUNTIFS(Data_Sheet!$E:$E,$A2,Data_Sheet!$F:$F,B$1) -> 5 | C2: =COUNTIFS(Data_Sheet!$E:$E,$A2,Data_Sheet!$F:$F,C$1) -> 0 | D2: =COUNTIFS(Data_Sheet!$E:$E,$A2,Data_Sheet!$F:$F,D$1) -> 1
A3: Tata Punch | B3: =COUNTIFS(Data_Sheet!$E:$E,$A3,Data_Sheet!$F:$F,B$1) -> 3 | C3: =COUNTIFS(Data_Sheet!$E:$E,$A3,Data_Sheet!$F:$F,C$1) -> 2 | D3: =COUNTIFS(Data_Sheet!$E:$E,$A3,Data_Sheet!$F:$F,D$1) -> 0
A4: Tata Tiago | B4: =COUNTIFS(Data_Sheet!$E:$E,$A4,Data_Sheet!$F:$F,B$1) -> 2 | C4: =COUNTIFS(Data_Sheet!$E:$E,$A4,Data_Sheet!$F:$F,C$1) -> 0 | D4: =COUNTIFS(Data_Sheet!$E:$E,$A4,Data_Sheet!$F:$F,D$1) -> 1
A5: Tata Harrier | B5: =COUNTIFS(Data_Sheet!$E:$E,$A5,Data_Sheet!$F:$F,B$1) -> 3 | C5: =COUNTIFS(Data_Sheet!$E:$E,$A5,Data_Sheet!$F:$F,C$1) -> 1 | D5: =COUNTIFS(Data_Sheet!$E:$E,$A5,Data_Sheet!$F:$F,D$1) -> 1
A6: Tata Safari | B6: =COUNTIFS(Data_Sheet!$E:$E,$A6,Data_Sheet!$F:$F,B$1) -> 3 | C6: =COUNTIFS(Data_Sheet!$E:$E,$A6,Data_Sheet!$F:$F,C$1) -> 1 | D6: =COUNTIFS(Data_Sheet!$E:$E,$A6,Data_Sheet!$F:$F,D$1) -> 1
A7: Tata Altroz | B7: =COUNTIFS(Data_Sheet!$E:$E,$A7,Data_Sheet!$F:$F,B$1) -> 4 | C7: =COUNTIFS(Data_Sheet!$E:$E,$A7,Data_Sheet!$F:$F,C$1) -> 1 | D7: =COUNTIFS(Data_Sheet!$E:$E,$A7,Data_Sheet!$F:$F,D$1) -> 0
A8: Tata Tigor | B8: =COUNTIFS(Data_Sheet!$E:$E,$A8,Data_Sheet!$F:$F,B$1) -> 4 | C8: =COUNTIFS(Data_Sheet!$E:$E,$A8,Data_Sheet!$F:$F,C$1) -> 1 | D8: =COUNTIFS(Data_Sheet!$E:$E,$A8,Data_Sheet!$F:$F,D$1) -> 0
A9: Tata Curvv | B9: =COUNTIFS(Data_Sheet!$E:$E,$A9,Data_Sheet!$F:$F,B$1) -> 4 | C9: =COUNTIFS(Data_Sheet!$E:$E,$A9,Data_Sheet!$F:$F,C$1) -> 1 | D9: =COUNTIFS(Data_Sheet!$E:$E,$A9,Data_Sheet!$F:$F,D$1) -> 0
A10: Tata Nexon EV | B10: =COUNTIFS(Data_Sheet!$E:$E,$A10,Data_Sheet!$F:$F,B$1) -> 2 | C10: =COUNTIFS(Data_Sheet!$E:$E,$A10,Data_Sheet!$F:$F,C$1) -> 1 | D10: =COUNTIFS(Data_Sheet!$E:$E,$A10,Data_Sheet!$F:$F,D$1) -> 1
A11: Tata Punch EV | B11: =COUNTIFS(Data_Sheet!$E:$E,$A11,Data_Sheet!$F:$F,B$1) -> 2 | C11: =COUNTIFS(Data_Sheet!$E:$E,$A11,Data_Sheet!$F:$F,C$1) -> 0 | D11: =COUNTIFS(Data_Sheet!$E:$E,$A11,Data_Sheet!$F:$F,D$1) -> 2
A12: Tata Tiago EV | B12: =COUNTIFS(Data_Sheet!$E:$E,$A12,Data_Sheet!$F:$F,B$1) -> 3 | C12: =COUNTIFS(Data_Sheet!$E:$E,$A12,Data_Sheet!$F:$F,C$1) -> 0 | D12: =COUNTIFS(Data_Sheet!$E:$E,$A12,Data_Sheet!$F:$F,D$1) -> 0
A13: Tata Altroz | B13: =COUNTIFS(Data_Sheet!$E:$E,$A13,Data_Sheet!$F:$F,B$1) -> 4 | C13: =COUNTIFS(Data_Sheet!$E:$E,$A13,Data_Sheet!$F:$F,C$1) -> 1 | D13: =COUNTIFS(Data_Sheet!$E:$E,$A13,Data_Sheet!$F:$F,D$1) -> 0
... A51: Tata Nexon | B51: =COUNTIFS(Data_Sheet!$E:$E,$A51,Data_Sheet!$F:$F,B$1) -> 5 | C51: =COUNTIFS(Data_Sheet!$E:$E,$A51,Data_Sheet!$F:$F,C$1) -> 0 | D51: =COUNTIFS(Data_Sheet!$E:$E,$A51,Data_Sheet!$F:$F,D$1) -> 1

Sheet city_wise_analysis
A1: City | B1: Cars Sold | C1: Total Sales | D1: Average Sale Price
A2: Metro | B2: =COUNTIFS(Data_Sheet!$C:$C,$A2,Data_Sheet!$F:$F,"Delivered") -> 17 | C2: =SUMIFS(Data_Sheet!$I:$I,Data_Sheet!$C:$C,$A2,Data_Sheet!$F:$F,"Delivered") -> 20984000 | D2: =AVERAGEIFS(Data_Sheet!$I:$I,Data_Sheet!$C:$C,$A2,Data_Sheet!$F:$F,"Delivered") -> 1234352.9
A3: Tier 1 | B3: =COUNTIFS(Data_Sheet!$C:$C,$A3,Data_Sheet!$F:$F,"Delivered") -> 11 | C3: =SUMIFS(Data_Sheet!$I:$I,Data_Sheet!$C:$C,$A3,Data_Sheet!$F:$F,"Delivered") -> 12229000 | D3: =AVERAGEIFS(Data_Sheet!$I:$I,Data_Sheet!$C:$C,$A3,Data_Sheet!$F:$F,"Delivered") -> 1111727.3
A4: Tier 2 | B4: =COUNTIFS(Data_Sheet!$C:$C,$A4,Data_Sheet!$F:$F,"Delivered") -> 7 | C4: =SUMIFS(Data_Sheet!$I:$I,Data_Sheet!$C:$C,$A4,Data_Sheet!$F:$F,"Delivered") -> 6797000 | D4: =AVERAGEIFS(Data_Sheet!$I:$I,Data_Sheet!$C:$C,$A4,Data_Sheet!$F:$F,"Delivered") -> 971000

Sheet Delivered pivot
A1: Row Labels | B1: Count of Delivery Status
A2: Tata Altroz | B2: 4
A3: Tata Curvv | B3: 4
A4: Tata Harrier | B4: 3
A5: Tata Nexon | B5: 5
A6: Tata Nexon EV | B6: 2
A7: Tata Punch | B7: 3
A8: Tata Punch EV | B8: 2
A9: Tata Safari | B9: 3
A10: Tata Tiago | B10: 2
A11: Tata Tiago EV | B11: 3
A12: Tata Tigor | B12: 4
A13: Grand Total | B13: 35

Sheet Sale_Report_Delivered
A1: Product_ID | B1: City_Category | C1: Batch | D1: Model Name | E1: Delivery Status | F1: Product Cost | G1: Final Price
A2: TATA001 | B2: Metro | C2: B001 | D2: Tata Nexon | E2: Delivered | F2: 780000 | G2: 900000
A3: TATA002 | B3: Tier 1 | C3: B001 | D3: Tata Punch | E3: Delivered | F3: 620000 | G3: 715000 | K3: Row Labels | L3: Sum of Cars Sold
A4: TATA003 | B4: Tier 2 | C4: B002 | D4: Tata Tiago | E4: Delivered | F4: 520000 | G4: 600000 | K4: Tier 1 | L4: 11
A5: TATA004 | B5: Metro | C5: B002 | D5: Tata Harrier | E5: Delivered | F5: 1450000 | G5: 1700000 | K5: Tier 2 | L5: 7
A6: TATA006 | B6: Metro | C6: B003 | D6: Tata Altroz | E6: Delivered | F6: 680000 | G6: 785000 | K6: Grand Total | L6: 18
A7: TATA007 | B7: Tier 2 | C7: B004 | D7: Tata Tigor | E7: Delivered | F7: 610000 | G7: 700000
A8: TATA009 | B8: Metro | C8: B005 | D8: Tata Nexon EV | E8: Delivered | F8: 1450000 | G8: 1630000
A9: TATA011 | B9: Metro | C9: B006 | D9: Tata Tiago EV | E9: Delivered | F9: 950000 | G9: 1080000
A10: TATA012 | B10: Tier 1 | C10: B006 | D10: Tata Altroz | E10: Delivered | F10: 720000 | G10: 830000
A11: TATA014 | B11: Metro | C11: B007 | D11: Tata Harrier | E11: Delivered | F11: 1520000 | G11: 1780000
A12: TATA015 | B12: Tier 1 | C12: B008 | D12: Tata Safari | E12: Delivered | F12: 1620000 | G12: 1900000
A13: TATA017 | B13: Metro | C13: B009 | D13: Tata Curvv | E13: Delivered | F13: 1100000 | G13: 1280000
A14: TATA018 | B14: Tier 1 | C14: B009 | D14: Tata Tigor | E14: Delivered | F14: 630000 | G14: 725000
A15: TATA019 | B15: Tier 2 | C15: B010 | D15: Tata Tiago | E15: Delivered | F15: 540000 | G15: 625000
A16: TATA021 | B16: Tier 1 | C16: B011 | D16: Tata Punch EV | E16: Delivered | F16: 1180000 | G16: 1340000
A17: TATA023 | B17: Tier 2 | C17: B012 | D17: Tata Nexon | E17: Delivered | F17: 800000 | G17: 922000
A18: TATA024 | B18: Metro | C18: B012 | D18: Tata Harrier | E18: Delivered | F18: 1480000 | G18: 1735000
... A36: TATA050 | B36: Metro | C36: B025 | D36: Tata Nexon | E36: Delivered | F36: 880000 | G36: 1015000

Sheet Sheet1
A1: Row Labels | B1: Sum of Product Cost | C1: Sum of Taxation & Delivery Cost
A2: Tata Altroz | B2: 3585000 | C2: 550000
A3: Tata Curvv | B3: 5500000 | C3: 908000
A4: Tata Harrier | B4: 7500000 | C4: 1288000
A5: Tata Nexon | B5: 5000000 | C5: 764000
A6: Tata Nexon EV | B6: 5950000 | C6: 750000
A7: Tata Punch | B7: 3255000 | C7: 498000
A8: Tata Punch EV | B8: 4750000 | C8: 648000
A9: Tata Safari | B9: 8000000 | C9: 1388000
A10: Tata Tiago | B10: 1610000 | C10: 250000
A11: Tata Tiago EV | B11: 2930000 | C11: 403000
A12: Tata Tigor | B12: 3170000 | C12: 475000
A13: Grand Total | B13: 51250000 | C13: 7922000
